pyqywe_token/__init__.py
pyqywe_token/basetoken.py
pyqywe_token/token.py
pyqywe_token-1.0.0.dist-info/METADATA
pyqywe_token-1.0.0.dist-info/WHEEL
pyqywe_token-1.0.0.dist-info/top_level.txt
pyqywe_token-1.0.0.dist-info/RECORD
